[{
  "dateTime" : "11/21/21 00:00:00",
  "value" : "837"
},{
  "dateTime" : "11/22/21 00:00:00",
  "value" : "903"
},{
  "dateTime" : "11/23/21 00:00:00",
  "value" : "878"
},{
  "dateTime" : "11/24/21 00:00:00",
  "value" : "1397"
},{
  "dateTime" : "11/25/21 00:00:00",
  "value" : "1091"
},{
  "dateTime" : "11/26/21 00:00:00",
  "value" : "1393"
},{
  "dateTime" : "11/27/21 00:00:00",
  "value" : "1123"
},{
  "dateTime" : "11/28/21 00:00:00",
  "value" : "1425"
},{
  "dateTime" : "11/29/21 00:00:00",
  "value" : "1164"
},{
  "dateTime" : "11/30/21 00:00:00",
  "value" : "1319"
},{
  "dateTime" : "12/01/21 00:00:00",
  "value" : "1226"
},{
  "dateTime" : "12/02/21 00:00:00",
  "value" : "1214"
},{
  "dateTime" : "12/03/21 00:00:00",
  "value" : "1328"
},{
  "dateTime" : "12/04/21 00:00:00",
  "value" : "952"
},{
  "dateTime" : "12/05/21 00:00:00",
  "value" : "1170"
},{
  "dateTime" : "12/06/21 00:00:00",
  "value" : "1266"
},{
  "dateTime" : "12/07/21 00:00:00",
  "value" : "1244"
},{
  "dateTime" : "12/08/21 00:00:00",
  "value" : "1192"
},{
  "dateTime" : "12/09/21 00:00:00",
  "value" : "852"
},{
  "dateTime" : "12/10/21 00:00:00",
  "value" : "1182"
},{
  "dateTime" : "12/11/21 00:00:00",
  "value" : "1272"
},{
  "dateTime" : "12/12/21 00:00:00",
  "value" : "1228"
},{
  "dateTime" : "12/13/21 00:00:00",
  "value" : "1198"
},{
  "dateTime" : "12/14/21 00:00:00",
  "value" : "1238"
},{
  "dateTime" : "12/15/21 00:00:00",
  "value" : "1296"
},{
  "dateTime" : "12/16/21 00:00:00",
  "value" : "1330"
},{
  "dateTime" : "12/17/21 00:00:00",
  "value" : "1258"
},{
  "dateTime" : "12/18/21 00:00:00",
  "value" : "1359"
},{
  "dateTime" : "12/19/21 00:00:00",
  "value" : "1173"
},{
  "dateTime" : "12/20/21 00:00:00",
  "value" : "1240"
}]